{
  "id": "",
  "typeInspection": "Pemeriksaan PAA Gantry Crane",
  "inspectionSchedule": "",
  "day": "",
  "time": null,
  "companyName": "",
  "companyLocation": "",
  "usageLocation": "",
  "location": "",
  "brandOrType": "",
  "manufacturer": "",
  "manufactureYear": null,
  "manufactureCountry": "",
  "serialNumber": "",
  "liftingPurpose": "Material dan Barang",
  "maxLiftingCapacityKg": null,
  "liftingSpeedMpm": null,
  "safetyEquipment": "Emergency stop",
  "viIsMainStructureGood": null,
  "viAreBoltsAndNutsSecure": null,
  "viIsWireRopeGood": null,
  "viIsHookGood": null,
  "viIsGearboxGood": null,
  "viHasGearboxOilLeak": null,
  "viIsWarningLampGood": null,
  "viIsCapacityMarkingDisplayed": null,
  "testIsForwardReverseOk": null,
  "testIsHoistingOk": null,
  "testIsLimitSwitchFunctional": null,
  "testNdtMethod": "",
  "testNdtIsResultGood": null,
  "testLoadKg": null,
  "testLiftHeightMeters": null,
  "testHoldTimeSeconds": null,
  "testLoadIsResultGood": null
}